README.txt
setup.py
src/Products/__init__.py
src/Products.GoPantsPockets.egg-info/PKG-INFO
src/Products.GoPantsPockets.egg-info/SOURCES.txt
src/Products.GoPantsPockets.egg-info/dependency_links.txt
src/Products.GoPantsPockets.egg-info/namespace_packages.txt
src/Products.GoPantsPockets.egg-info/not-zip-safe
src/Products.GoPantsPockets.egg-info/requires.txt
src/Products.GoPantsPockets.egg-info/top_level.txt
src/Products/GoPantsPockets/GoPantsPockets.py
src/Products/GoPantsPockets/IRemoteQueryServer.py
src/Products/GoPantsPockets/InteractiveInput.py
src/Products/GoPantsPockets/KeyValuePair.py
src/Products/GoPantsPockets/LocalInstance.py
src/Products/GoPantsPockets/QueryParameters.py
src/Products/GoPantsPockets/RESTServer.py
src/Products/GoPantsPockets/RemoteQueryServer.py
src/Products/GoPantsPockets/RewriteRule.py
src/Products/GoPantsPockets/SortRule.py
src/Products/GoPantsPockets/StoredQuery.py
src/Products/GoPantsPockets/XMLRPCServer.py
src/Products/GoPantsPockets/__init__.py
src/Products/GoPantsPockets/config.py
src/Products/GoPantsPockets/gopantspockets_page.py
src/Products/GoPantsPockets/gopantspockets_portlet.py
src/Products/GoPantsPockets/interfaces.py
src/Products/GoPantsPockets/setuphandlers.py
src/Products/GoPantsPockets/xml2dict.py