Metadata-Version: 1.0
Name: Products.GoPantsPockets
Version: 1.0.0
Summary: Products.GoPantsPockets
Home-page: UNKNOWN
Author: Georg Gogo BERNHARD
Author-email: gogo@bluedynamics.com
License: UNKNOWN
Platform: UNKNOWN
Classifier: Development Status :: 4 - Beta
Classifier: Environment :: Web Environment
Classifier: Framework :: Plone
Classifier: Operating System :: OS Independent
Classifier: Programming Language :: Python
